markforge/__init__.py
markforge/__main__.py
markforge/cli.py
markforge/core.py
markforge/gui.py
markforge/static/index.html
markforge-0.1.1.dist-info/METADATA
markforge-0.1.1.dist-info/WHEEL
markforge-0.1.1.dist-info/entry_points.txt
markforge-0.1.1.dist-info/licenses/LICENSE
markforge-0.1.1.dist-info/RECORD
