Metadata-Version: 2.4
Name: markforge
Version: 0.1.1
Summary: Text watermark/stamp tool (CLI-first, GUI-ready).
Project-URL: Homepage, https://github.com/remgrandt/markforge
Project-URL: Repository, https://github.com/remgrandt/markforge
Author: Grant
License: Markforge License
License-File: LICENSE
Keywords: cli,image,pillow,typer,watermark
Classifier: License :: Other/Proprietary License
Classifier: Operating System :: OS Independent
Classifier: Programming Language :: Python :: 3
Classifier: Programming Language :: Python :: 3.10
Classifier: Programming Language :: Python :: 3.11
Classifier: Programming Language :: Python :: 3.12
Classifier: Programming Language :: Python :: 3.13
Classifier: Topic :: Multimedia :: Graphics
Classifier: Topic :: Utilities
Requires-Python: >=3.10
Requires-Dist: pillow>=10.0.0
Requires-Dist: typer>=0.12.0
Provides-Extra: dev
Requires-Dist: pytest>=8.0.0; extra == 'dev'
Requires-Dist: ruff>=0.6.0; extra == 'dev'
Provides-Extra: gui
